varroa/__init__.py
varroa/app.py
varroa/extensions.py
varroa/manager.py
varroa/models.py
varroa/policy.py
varroa/version.py
varroa/wsgi.py
varroa/api/__init__.py
varroa/api/v1/__init__.py
varroa/api/v1/resources/__init__.py
varroa/api/v1/resources/base.py
varroa/api/v1/resources/ip_usage.py
varroa/api/v1/resources/security_risk.py
varroa/api/v1/resources/security_risk_type.py
varroa/api/v1/schemas/__init__.py
varroa/api/v1/schemas/ip_usage.py
varroa/api/v1/schemas/security_risk.py
varroa/api/v1/schemas/security_risk_type.py
varroa/cmd/__init__.py
varroa/cmd/api.py
varroa/cmd/manage.py
varroa/cmd/notification.py
varroa/cmd/worker.py
varroa/common/__init__.py
varroa/common/clients.py
varroa/common/config.py
varroa/common/exceptions.py
varroa/common/keystone.py
varroa/common/policies.py
varroa/common/rpc.py
varroa/common/service.py
varroa/common/utils.py
varroa/migrations/README
varroa/migrations/alembic.ini
varroa/migrations/env.py
varroa/migrations/script.py.mako
varroa/migrations/versions/5069a0e63566_add_security_risks.py
varroa/migrations/versions/b2713bc943c2_initial_migration.py
varroa/notification/__init__.py
varroa/notification/consumer.py
varroa/notification/endpoints.py
varroa/tests/__init__.py
varroa/tests/etc/varroa.conf
varroa/tests/unit/__init__.py
varroa/tests/unit/base.py
varroa/tests/unit/test_manager.py
varroa/tests/unit/test_models.py
varroa/tests/unit/api/__init__.py
varroa/tests/unit/api/v1/__init__.py
varroa/tests/unit/api/v1/test_ip_usage.py
varroa/tests/unit/api/v1/test_security_risk_types.py
varroa/tests/unit/api/v1/test_security_risks.py
varroa/tests/unit/common/__init__.py
varroa/tests/unit/common/test_keystone.py
varroa/tests/unit/common/test_utils.py
varroa/tests/unit/notification/__init__.py
varroa/tests/unit/notification/test_endpoints.py
varroa/tests/unit/worker/__init__.py
varroa/tests/unit/worker/test_manager.py
varroa/worker/__init__.py
varroa/worker/api.py
varroa/worker/consumer.py
varroa/worker/endpoints.py
varroa-0.11.1.dist-info/LICENSE
varroa-0.11.1.dist-info/METADATA
varroa-0.11.1.dist-info/WHEEL
varroa-0.11.1.dist-info/entry_points.txt
varroa-0.11.1.dist-info/pbr.json
varroa-0.11.1.dist-info/top_level.txt
varroa-0.11.1.dist-info/RECORD
