Metadata-Version: 2.1
Name: varroa
Version: 0.11.1
Summary: Vulnerability management for Opentack
Home-page: https://github.com/NeCTAR-RC/varroa
Author: ARDC Nectar Cloud Services
Author-email: coreservices@ardc.edu.au
License: Apache-2.0
Keywords: varroa
Classifier: Environment :: OpenStack
Classifier: Intended Audience :: Information Technology
Classifier: Intended Audience :: System Administrators
Classifier: License :: OSI Approved :: Apache Software License
Classifier: Operating System :: POSIX :: Linux
Classifier: Programming Language :: Python
Classifier: Programming Language :: Python :: 3 :: Only
Classifier: Programming Language :: Python :: 3
Classifier: Programming Language :: Python :: 3.10
Classifier: Programming Language :: Python :: 3.12
License-File: LICENSE
Requires-Dist: pbr
Requires-Dist: openstacksdk
Requires-Dist: keystoneauth1
Requires-Dist: keystonemiddleware
Requires-Dist: oslo.context
Requires-Dist: oslo.config
Requires-Dist: oslo.log
Requires-Dist: oslo.messaging
Requires-Dist: oslo.policy
Requires-Dist: flask>=1.0.2
Requires-Dist: marshmallow>=3.4.0
Requires-Dist: flask-migrate>=2.1.1
Requires-Dist: flask-restful>=0.3.6
Requires-Dist: flask-sqlalchemy>=2.4.1
Requires-Dist: flask-marshmallow>=0.11.0
Requires-Dist: marshmallow-sqlalchemy>=0.22.3
Requires-Dist: cotyledon
Requires-Dist: pymysql
Requires-Dist: python-memcached
